mosaicode_lib_javascript_webaudio
