Metadata-Version: 1.2
Name: mosaicode-lib-javascript-webaudio
Version: 1.0.3.dev1
Summary: Computer Music Programming Tool
Home-page: https://mosaicode.github.io/
Author: ALICE: Arts Lab in Interfaces, Computers, and Experiences
Author-email: mosaicode-dev@googlegroups.com
Maintainer: ALICE: Arts Lab in Interfaces, Computers, and Experiences
Maintainer-email: mosaicode-dev@googlegroups.com
License: GNU GPL3
Platform: UNKNOWN
Classifier: Development Status :: 3 - Alpha
Classifier: Intended Audience :: Developers
Classifier: Intended Audience :: Science/Research
Classifier: License :: OSI Approved :: GNU General Public License (GPL)
Classifier: Natural Language :: English
Classifier: Operating System :: OS Independent
Classifier: Programming Language :: Python
Classifier: Programming Language :: JavaScript
Classifier: Topic :: Scientific/Engineering
Classifier: Topic :: Software Development :: Code Generators
Requires-Python: >=2.7
